pineapple/__init__.py
pineapple/client.py
pineapple/pager.py
pineapple/payloads.py
pineapple/recon.py
pineapple_pager_api-0.1.0.dist-info/licenses/LICENSE
pineapple_pager_api-0.1.0.dist-info/METADATA
pineapple_pager_api-0.1.0.dist-info/WHEEL
pineapple_pager_api-0.1.0.dist-info/top_level.txt
pineapple_pager_api-0.1.0.dist-info/RECORD
