Metadata-Version: 2.4
Name: pineapple-pager-api
Version: 0.1.0
Summary: Python library for interacting with Pineapple Pager devices
Author: tpollard64
License: MIT
Requires-Python: >=3.7
License-File: LICENSE
Requires-Dist: paramiko
Dynamic: license-file
